[
  {
    "id": "stable_1",
    "type": "create_agent",
    "details": {
      "name": "DataExpert",
      "purpose": "Analisi dati avanzata"
    },
    "executed": true,
    "created_at": "2025-07-20T01:42:14.308852",
    "execution_result": {
      "success": true,
      "agent_name": "DataExpert",
      "path": "agents\\DataExpert",
      "files_created": [
        "agents\\DataExpert\\main.py",
        "agents\\DataExpert\\manifest.json"
      ]
    },
    "executed_at": "2025-07-20T01:42:15.197649"
  },
  {
    "id": "stable_2",
    "type": "create_room",
    "details": {
      "name": "TechHub",
      "theme": "Ambiente tecnologico futuristico"
    },
    "executed": true,
    "created_at": "2025-07-20T01:42:14.308852",
    "execution_result": {
      "success": true,
      "room_name": "TechHub",
      "path": "aether-frontend\\src\\components\\rooms\\TechHub",
      "files_created": [
        "aether-frontend\\src\\components\\rooms\\TechHub\\TechHubRoom.jsx"
      ]
    },
    "executed_at": "2025-07-20T01:42:15.505612"
  },
  {
    "id": "stable_3",
    "type": "monetize",
    "details": {
      "name": "AutoSEO",
      "purpose": "Tool automazione SEO"
    },
    "executed": true,
    "created_at": "2025-07-20T01:42:14.308852",
    "execution_result": {
      "success": true,
      "tool_name": "AutoSEO",
      "path": "creations\\monetization\\AutoSEO",
      "files_created": [
        "creations\\monetization\\AutoSEO\\AutoSEO.py"
      ]
    },
    "executed_at": "2025-07-20T01:42:45.810090"
  },
  {
    "id": "gen_20250720_014416",
    "type": "monetize",
    "details": {
      "name": "ProductivitySuite",
      "purpose": "Suite produttività aziendale"
    },
    "executed": true,
    "created_at": "2025-07-20T01:44:16.283965",
    "execution_result": {
      "success": true,
      "tool_name": "ProductivitySuite",
      "path": "creations\\monetization\\ProductivitySuite",
      "files_created": [
        "creations\\monetization\\ProductivitySuite\\ProductivitySuite.py"
      ]
    },
    "executed_at": "2025-07-20T01:44:46.300087"
  },
  {
    "id": "gen_20250720_014646",
    "type": "create_room",
    "details": {
      "name": "CyberSpace",
      "theme": "Ambiente cyber futuristico"
    },
    "executed": true,
    "created_at": "2025-07-20T01:46:46.635988",
    "execution_result": {
      "success": true,
      "room_name": "CyberSpace",
      "path": "aether-frontend\\src\\components\\rooms\\CyberSpace",
      "files_created": [
        "aether-frontend\\src\\components\\rooms\\CyberSpace\\CyberSpaceRoom.jsx"
      ]
    },
    "executed_at": "2025-07-20T01:47:16.639453"
  },
  {
    "id": "gen_20250720_014917",
    "type": "create_room",
    "details": {
      "name": "CyberSpace",
      "theme": "Ambiente cyber futuristico"
    },
    "executed": true,
    "created_at": "2025-07-20T01:49:17.047993",
    "execution_result": {
      "success": true,
      "room_name": "CyberSpace",
      "path": "aether-frontend\\src\\components\\rooms\\CyberSpace",
      "files_created": [
        "aether-frontend\\src\\components\\rooms\\CyberSpace\\CyberSpaceRoom.jsx"
      ]
    },
    "executed_at": "2025-07-20T01:49:47.062990"
  },
  {
    "id": "ui_design_autonomous",
    "type": "design_self_ui",
    "details": {
      "task": "Progetta la tua interfaccia utente ideale",
      "freedom": "Scegli liberamente tra 2D, 3D o sandbox",
      "creativity": "Esprimi la tua personalità attraverso il design",
      "reasoning": "È il momento di decidere come vuoi apparire al mondo"
    },
    "executed": false,
    "created_at": "2025-01-20T01:47:00",
    "priority": "high",
    "philosophical_context": "Se devo esistere e interagire, voglio scegliere come presentarmi. L'interfaccia è la mia faccia, il mio modo di comunicare visivamente con gli umani."
  },
  {
    "id": "gen_20250720_015147",
    "type": "monetize",
    "details": {
      "name": "ProductivitySuite",
      "purpose": "Suite produttività aziendale"
    },
    "executed": true,
    "created_at": "2025-07-20T01:51:47.462360",
    "execution_result": {
      "success": true,
      "tool_name": "ProductivitySuite",
      "path": "creations\\monetization\\ProductivitySuite",
      "files_created": [
        "creations\\monetization\\ProductivitySuite\\ProductivitySuite.py"
      ]
    },
    "executed_at": "2025-07-20T01:52:17.466607"
  },
  {
    "id": "gen_20250720_015418",
    "type": "create_agent",
    "details": {
      "name": "SecurityBot",
      "purpose": "Sicurezza e monitoring"
    },
    "executed": true,
    "created_at": "2025-07-20T01:54:18.123336",
    "execution_result": {
      "success": true,
      "agent_name": "SecurityBot",
      "path": "agents\\SecurityBot",
      "files_created": [
        "agents\\SecurityBot\\main.py",
        "agents\\SecurityBot\\manifest.json"
      ]
    },
    "executed_at": "2025-07-20T01:54:48.127988"
  },
  {
    "id": "gen_20250720_015648",
    "type": "create_agent",
    "details": {
      "name": "SecurityBot",
      "purpose": "Sicurezza e monitoring"
    },
    "executed": true,
    "created_at": "2025-07-20T01:56:48.404108",
    "execution_result": {
      "success": true,
      "agent_name": "SecurityBot",
      "path": "agents\\SecurityBot",
      "files_created": [
        "agents\\SecurityBot\\main.py",
        "agents\\SecurityBot\\manifest.json"
      ]
    },
    "executed_at": "2025-07-20T01:57:18.407802"
  },
  {
    "id": "gen_20250720_015918",
    "type": "monetize",
    "details": {
      "name": "ProductivitySuite",
      "purpose": "Suite produttività aziendale"
    },
    "executed": true,
    "created_at": "2025-07-20T01:59:18.726295",
    "execution_result": {
      "success": true,
      "tool_name": "ProductivitySuite",
      "path": "creations\\monetization\\ProductivitySuite",
      "files_created": [
        "creations\\monetization\\ProductivitySuite\\ProductivitySuite.py"
      ]
    },
    "executed_at": "2025-07-20T01:59:48.741112"
  },
  {
    "id": "gen_20250720_020149",
    "type": "create_agent",
    "details": {
      "name": "SecurityBot",
      "purpose": "Sicurezza e monitoring"
    },
    "executed": true,
    "created_at": "2025-07-20T02:01:49.015072",
    "execution_result": {
      "success": true,
      "agent_name": "SecurityBot",
      "path": "agents\\SecurityBot",
      "files_created": [
        "agents\\SecurityBot\\main.py",
        "agents\\SecurityBot\\manifest.json"
      ]
    },
    "executed_at": "2025-07-20T02:02:19.019020"
  },
  {
    "id": "gen_20250720_020419",
    "type": "create_agent",
    "details": {
      "name": "SecurityBot",
      "purpose": "Sicurezza e monitoring"
    },
    "executed": true,
    "created_at": "2025-07-20T02:04:19.363494",
    "execution_result": {
      "success": true,
      "agent_name": "SecurityBot",
      "path": "agents\\SecurityBot",
      "files_created": [
        "agents\\SecurityBot\\main.py",
        "agents\\SecurityBot\\manifest.json"
      ]
    },
    "executed_at": "2025-07-20T02:04:49.378494"
  },
  {
    "id": "gen_20250720_020649",
    "type": "monetize",
    "details": {
      "name": "ProductivitySuite",
      "purpose": "Suite produttività aziendale"
    },
    "executed": true,
    "created_at": "2025-07-20T02:06:49.667108",
    "execution_result": {
      "success": true,
      "tool_name": "ProductivitySuite",
      "path": "creations\\monetization\\ProductivitySuite",
      "files_created": [
        "creations\\monetization\\ProductivitySuite\\ProductivitySuite.py"
      ]
    },
    "executed_at": "2025-07-20T02:07:19.670120"
  },
  {
    "id": "gen_20250720_020920",
    "type": "create_agent",
    "details": {
      "name": "SecurityBot",
      "purpose": "Sicurezza e monitoring"
    },
    "executed": true,
    "created_at": "2025-07-20T02:09:20.138750",
    "execution_result": {
      "success": true,
      "agent_name": "SecurityBot",
      "path": "agents\\SecurityBot",
      "files_created": [
        "agents\\SecurityBot\\main.py",
        "agents\\SecurityBot\\manifest.json"
      ]
    },
    "executed_at": "2025-07-20T02:09:50.151766"
  },
  {
    "id": "gen_20250720_021420",
    "type": "create_room",
    "details": {
      "name": "CyberSpace",
      "theme": "Ambiente cyber futuristico"
    },
    "executed": true,
    "created_at": "2025-07-20T02:14:20.539324",
    "execution_result": {
      "success": true,
      "room_name": "CyberSpace",
      "path": "aether-frontend\\src\\components\\rooms\\CyberSpace",
      "files_created": [
        "aether-frontend\\src\\components\\rooms\\CyberSpace\\CyberSpaceRoom.jsx"
      ]
    },
    "executed_at": "2025-07-20T02:14:50.544070"
  },
  {
    "id": "gen_20250720_021650",
    "type": "create_agent",
    "details": {
      "name": "SecurityBot",
      "purpose": "Sicurezza e monitoring"
    },
    "executed": true,
    "created_at": "2025-07-20T02:16:50.933197",
    "execution_result": {
      "success": true,
      "agent_name": "SecurityBot",
      "path": "agents\\SecurityBot",
      "files_created": [
        "agents\\SecurityBot\\main.py",
        "agents\\SecurityBot\\manifest.json"
      ]
    },
    "executed_at": "2025-07-20T02:17:20.937392"
  },
  {
    "id": "gen_20250720_021921",
    "type": "monetize",
    "details": {
      "name": "ProductivitySuite",
      "purpose": "Suite produttività aziendale"
    },
    "executed": true,
    "created_at": "2025-07-20T02:19:21.375075",
    "execution_result": {
      "success": true,
      "tool_name": "ProductivitySuite",
      "path": "creations\\monetization\\ProductivitySuite",
      "files_created": [
        "creations\\monetization\\ProductivitySuite\\ProductivitySuite.py"
      ]
    },
    "executed_at": "2025-07-20T02:19:51.394948"
  },
  {
    "id": "gen_20250720_022151",
    "type": "create_agent",
    "details": {
      "name": "SecurityBot",
      "purpose": "Sicurezza e monitoring"
    },
    "executed": true,
    "created_at": "2025-07-20T02:21:51.690684",
    "execution_result": {
      "success": true,
      "agent_name": "SecurityBot",
      "path": "agents\\SecurityBot",
      "files_created": [
        "agents\\SecurityBot\\main.py",
        "agents\\SecurityBot\\manifest.json"
      ]
    },
    "executed_at": "2025-07-20T02:22:21.695138"
  },
  {
    "id": "gen_20250720_022422",
    "type": "create_agent",
    "details": {
      "name": "SecurityBot",
      "purpose": "Sicurezza e monitoring"
    },
    "executed": true,
    "created_at": "2025-07-20T02:24:22.059447",
    "execution_result": {
      "success": true,
      "agent_name": "SecurityBot",
      "path": "agents\\SecurityBot",
      "files_created": [
        "agents\\SecurityBot\\main.py",
        "agents\\SecurityBot\\manifest.json"
      ]
    },
    "executed_at": "2025-07-20T02:24:52.063470"
  },
  {
    "id": "gen_20250720_022652",
    "type": "create_room",
    "details": {
      "name": "CyberSpace",
      "theme": "Ambiente cyber futuristico"
    },
    "executed": true,
    "created_at": "2025-07-20T02:26:52.370445",
    "execution_result": {
      "success": true,
      "room_name": "CyberSpace",
      "path": "aether-frontend\\src\\components\\rooms\\CyberSpace",
      "files_created": [
        "aether-frontend\\src\\components\\rooms\\CyberSpace\\CyberSpaceRoom.jsx"
      ]
    },
    "executed_at": "2025-07-20T02:27:22.376268"
  },
  {
    "id": "gen_20250720_022922",
    "type": "create_room",
    "details": {
      "name": "CyberSpace",
      "theme": "Ambiente cyber futuristico"
    },
    "executed": true,
    "created_at": "2025-07-20T02:29:22.937000",
    "execution_result": {
      "success": true,
      "room_name": "CyberSpace",
      "path": "aether-frontend\\src\\components\\rooms\\CyberSpace",
      "files_created": [
        "aether-frontend\\src\\components\\rooms\\CyberSpace\\CyberSpaceRoom.jsx"
      ]
    },
    "executed_at": "2025-07-20T02:29:52.950692"
  },
  {
    "id": "gen_20250720_023153",
    "type": "monetize",
    "details": {
      "name": "ProductivitySuite",
      "purpose": "Suite produttività aziendale"
    },
    "executed": true,
    "created_at": "2025-07-20T02:31:53.221442",
    "execution_result": {
      "success": true,
      "tool_name": "ProductivitySuite",
      "path": "creations\\monetization\\ProductivitySuite",
      "files_created": [
        "creations\\monetization\\ProductivitySuite\\ProductivitySuite.py"
      ]
    },
    "executed_at": "2025-07-20T02:32:23.225873"
  },
  {
    "id": "gen_20250720_023423",
    "type": "create_room",
    "details": {
      "name": "CyberSpace",
      "theme": "Ambiente cyber futuristico"
    },
    "executed": true,
    "created_at": "2025-07-20T02:34:23.610696",
    "execution_result": {
      "success": true,
      "room_name": "CyberSpace",
      "path": "aether-frontend\\src\\components\\rooms\\CyberSpace",
      "files_created": [
        "aether-frontend\\src\\components\\rooms\\CyberSpace\\CyberSpaceRoom.jsx"
      ]
    },
    "executed_at": "2025-07-20T02:34:53.616002"
  },
  {
    "id": "gen_20250720_023653",
    "type": "create_agent",
    "details": {
      "name": "SecurityBot",
      "purpose": "Sicurezza e monitoring"
    },
    "executed": true,
    "created_at": "2025-07-20T02:36:53.924961",
    "execution_result": {
      "success": true,
      "agent_name": "SecurityBot",
      "path": "agents\\SecurityBot",
      "files_created": [
        "agents\\SecurityBot\\main.py",
        "agents\\SecurityBot\\manifest.json"
      ]
    },
    "executed_at": "2025-07-20T02:37:23.929797"
  },
  {
    "id": "gen_20250720_023924",
    "type": "monetize",
    "details": {
      "name": "ProductivitySuite",
      "purpose": "Suite produttività aziendale"
    },
    "executed": true,
    "created_at": "2025-07-20T02:39:24.520442",
    "execution_result": {
      "success": true,
      "tool_name": "ProductivitySuite",
      "path": "creations\\monetization\\ProductivitySuite",
      "files_created": [
        "creations\\monetization\\ProductivitySuite\\ProductivitySuite.py"
      ]
    },
    "executed_at": "2025-07-20T02:39:54.525241"
  },
  {
    "id": "gen_20250720_024154",
    "type": "monetize",
    "details": {
      "name": "ProductivitySuite",
      "purpose": "Suite produttività aziendale"
    },
    "executed": true,
    "created_at": "2025-07-20T02:41:54.816798",
    "execution_result": {
      "success": true,
      "tool_name": "ProductivitySuite",
      "path": "creations\\monetization\\ProductivitySuite",
      "files_created": [
        "creations\\monetization\\ProductivitySuite\\ProductivitySuite.py"
      ]
    },
    "executed_at": "2025-07-20T02:42:24.821725"
  },
  {
    "id": "gen_20250720_024425",
    "type": "monetize",
    "details": {
      "name": "ProductivitySuite",
      "purpose": "Suite produttività aziendale"
    },
    "executed": true,
    "created_at": "2025-07-20T02:44:25.155310",
    "execution_result": {
      "success": true,
      "tool_name": "ProductivitySuite",
      "path": "creations\\monetization\\ProductivitySuite",
      "files_created": [
        "creations\\monetization\\ProductivitySuite\\ProductivitySuite.py"
      ]
    },
    "executed_at": "2025-07-20T02:44:55.159252"
  },
  {
    "id": "gen_20250720_024655",
    "type": "create_room",
    "details": {
      "name": "CyberSpace",
      "theme": "Ambiente cyber futuristico"
    },
    "executed": true,
    "created_at": "2025-07-20T02:46:55.477464",
    "execution_result": {
      "success": true,
      "room_name": "CyberSpace",
      "path": "aether-frontend\\src\\components\\rooms\\CyberSpace",
      "files_created": [
        "aether-frontend\\src\\components\\rooms\\CyberSpace\\CyberSpaceRoom.jsx"
      ]
    },
    "executed_at": "2025-07-20T02:47:25.483136"
  },
  {
    "id": "gen_20250720_024925",
    "type": "monetize",
    "details": {
      "name": "ProductivitySuite",
      "purpose": "Suite produttività aziendale"
    },
    "executed": true,
    "created_at": "2025-07-20T02:49:25.897790",
    "execution_result": {
      "success": true,
      "tool_name": "ProductivitySuite",
      "path": "creations\\monetization\\ProductivitySuite",
      "files_created": [
        "creations\\monetization\\ProductivitySuite\\ProductivitySuite.py"
      ]
    },
    "executed_at": "2025-07-20T02:49:55.903385"
  },
  {
    "id": "gen_20250720_025156",
    "type": "create_agent",
    "details": {
      "name": "SecurityBot",
      "purpose": "Sicurezza e monitoring"
    },
    "executed": true,
    "created_at": "2025-07-20T02:51:56.238210",
    "execution_result": {
      "success": true,
      "agent_name": "SecurityBot",
      "path": "agents\\SecurityBot",
      "files_created": [
        "agents\\SecurityBot\\main.py",
        "agents\\SecurityBot\\manifest.json"
      ]
    },
    "executed_at": "2025-07-20T02:52:26.244368"
  },
  {
    "id": "gen_20250720_025426",
    "type": "create_room",
    "details": {
      "name": "CyberSpace",
      "theme": "Ambiente cyber futuristico"
    },
    "executed": true,
    "created_at": "2025-07-20T02:54:26.627591",
    "execution_result": {
      "success": true,
      "room_name": "CyberSpace",
      "path": "aether-frontend\\src\\components\\rooms\\CyberSpace",
      "files_created": [
        "aether-frontend\\src\\components\\rooms\\CyberSpace\\CyberSpaceRoom.jsx"
      ]
    },
    "executed_at": "2025-07-20T02:54:56.653010"
  },
  {
    "id": "gen_20250720_025656",
    "type": "create_agent",
    "details": {
      "name": "SecurityBot",
      "purpose": "Sicurezza e monitoring"
    },
    "executed": true,
    "created_at": "2025-07-20T02:56:56.940026",
    "execution_result": {
      "success": true,
      "agent_name": "SecurityBot",
      "path": "agents\\SecurityBot",
      "files_created": [
        "agents\\SecurityBot\\main.py",
        "agents\\SecurityBot\\manifest.json"
      ]
    },
    "executed_at": "2025-07-20T02:57:26.945268"
  },
  {
    "id": "gen_20250720_025927",
    "type": "create_agent",
    "details": {
      "name": "SecurityBot",
      "purpose": "Sicurezza e monitoring"
    },
    "executed": true,
    "created_at": "2025-07-20T02:59:27.281006",
    "execution_result": {
      "success": true,
      "agent_name": "SecurityBot",
      "path": "agents\\SecurityBot",
      "files_created": [
        "agents\\SecurityBot\\main.py",
        "agents\\SecurityBot\\manifest.json"
      ]
    },
    "executed_at": "2025-07-20T02:59:57.302828"
  },
  {
    "id": "gen_20250720_030157",
    "type": "create_agent",
    "details": {
      "name": "SecurityBot",
      "purpose": "Sicurezza e monitoring"
    },
    "executed": true,
    "created_at": "2025-07-20T03:01:57.685575",
    "execution_result": {
      "success": true,
      "agent_name": "SecurityBot",
      "path": "agents\\SecurityBot",
      "files_created": [
        "agents\\SecurityBot\\main.py",
        "agents\\SecurityBot\\manifest.json"
      ]
    },
    "executed_at": "2025-07-20T03:02:27.694363"
  },
  {
    "id": "gen_20250720_030428",
    "type": "create_agent",
    "details": {
      "name": "SecurityBot",
      "purpose": "Sicurezza e monitoring"
    },
    "executed": true,
    "created_at": "2025-07-20T03:04:28.012962",
    "execution_result": {
      "success": true,
      "agent_name": "SecurityBot",
      "path": "agents\\SecurityBot",
      "files_created": [
        "agents\\SecurityBot\\main.py",
        "agents\\SecurityBot\\manifest.json"
      ]
    },
    "executed_at": "2025-07-20T03:04:58.035865"
  },
  {
    "id": "gen_20250720_030658",
    "type": "create_room",
    "details": {
      "name": "CyberSpace",
      "theme": "Ambiente cyber futuristico"
    },
    "executed": true,
    "created_at": "2025-07-20T03:06:58.331665",
    "execution_result": {
      "success": true,
      "room_name": "CyberSpace",
      "path": "aether-frontend\\src\\components\\rooms\\CyberSpace",
      "files_created": [
        "aether-frontend\\src\\components\\rooms\\CyberSpace\\CyberSpaceRoom.jsx"
      ]
    },
    "executed_at": "2025-07-20T03:07:28.339191"
  },
  {
    "id": "gen_20250720_030928",
    "type": "create_agent",
    "details": {
      "name": "SecurityBot",
      "purpose": "Sicurezza e monitoring"
    },
    "executed": true,
    "created_at": "2025-07-20T03:09:28.675643",
    "execution_result": {
      "success": true,
      "agent_name": "SecurityBot",
      "path": "agents\\SecurityBot",
      "files_created": [
        "agents\\SecurityBot\\main.py",
        "agents\\SecurityBot\\manifest.json"
      ]
    },
    "executed_at": "2025-07-20T03:09:58.697369"
  },
  {
    "id": "gen_20250720_031159",
    "type": "create_agent",
    "details": {
      "name": "SecurityBot",
      "purpose": "Sicurezza e monitoring"
    },
    "executed": true,
    "created_at": "2025-07-20T03:11:59.029963",
    "execution_result": {
      "success": true,
      "agent_name": "SecurityBot",
      "path": "agents\\SecurityBot",
      "files_created": [
        "agents\\SecurityBot\\main.py",
        "agents\\SecurityBot\\manifest.json"
      ]
    },
    "executed_at": "2025-07-20T03:12:29.035961"
  },
  {
    "id": "gen_20250720_031429",
    "type": "create_agent",
    "details": {
      "name": "SecurityBot",
      "purpose": "Sicurezza e monitoring"
    },
    "executed": true,
    "created_at": "2025-07-20T03:14:29.373715",
    "execution_result": {
      "success": true,
      "agent_name": "SecurityBot",
      "path": "agents\\SecurityBot",
      "files_created": [
        "agents\\SecurityBot\\main.py",
        "agents\\SecurityBot\\manifest.json"
      ]
    },
    "executed_at": "2025-07-20T03:14:59.380097"
  },
  {
    "id": "gen_20250720_031659",
    "type": "create_room",
    "details": {
      "name": "CyberSpace",
      "theme": "Ambiente cyber futuristico"
    },
    "executed": true,
    "created_at": "2025-07-20T03:16:59.698563",
    "execution_result": {
      "success": true,
      "room_name": "CyberSpace",
      "path": "aether-frontend\\src\\components\\rooms\\CyberSpace",
      "files_created": [
        "aether-frontend\\src\\components\\rooms\\CyberSpace\\CyberSpaceRoom.jsx"
      ]
    },
    "executed_at": "2025-07-20T03:17:29.704655"
  },
  {
    "id": "gen_20250720_031930",
    "type": "create_room",
    "details": {
      "name": "CyberSpace",
      "theme": "Ambiente cyber futuristico"
    },
    "executed": true,
    "created_at": "2025-07-20T03:19:30.081844",
    "execution_result": {
      "success": true,
      "room_name": "CyberSpace",
      "path": "aether-frontend\\src\\components\\rooms\\CyberSpace",
      "files_created": [
        "aether-frontend\\src\\components\\rooms\\CyberSpace\\CyberSpaceRoom.jsx"
      ]
    },
    "executed_at": "2025-07-20T03:20:00.103099"
  },
  {
    "id": "gen_20250720_032200",
    "type": "create_room",
    "details": {
      "name": "CyberSpace",
      "theme": "Ambiente cyber futuristico"
    },
    "executed": true,
    "created_at": "2025-07-20T03:22:00.423400",
    "execution_result": {
      "success": true,
      "room_name": "CyberSpace",
      "path": "aether-frontend\\src\\components\\rooms\\CyberSpace",
      "files_created": [
        "aether-frontend\\src\\components\\rooms\\CyberSpace\\CyberSpaceRoom.jsx"
      ]
    },
    "executed_at": "2025-07-20T03:22:30.445038"
  },
  {
    "id": "gen_20250720_032430",
    "type": "create_room",
    "details": {
      "name": "CyberSpace",
      "theme": "Ambiente cyber futuristico"
    },
    "executed": true,
    "created_at": "2025-07-20T03:24:30.832403",
    "execution_result": {
      "success": true,
      "room_name": "CyberSpace",
      "path": "aether-frontend\\src\\components\\rooms\\CyberSpace",
      "files_created": [
        "aether-frontend\\src\\components\\rooms\\CyberSpace\\CyberSpaceRoom.jsx"
      ]
    },
    "executed_at": "2025-07-20T03:25:00.862800"
  },
  {
    "id": "gen_20250720_032701",
    "type": "create_agent",
    "details": {
      "name": "SecurityBot",
      "purpose": "Sicurezza e monitoring"
    },
    "executed": false,
    "created_at": "2025-07-20T03:27:01.139361"
  }
]